mutract/__init__.py
mutract/mutract.py
mutract/tests.py
mutract/utils.py
mutract-1.1.dist-info/METADATA
mutract-1.1.dist-info/WHEEL
mutract-1.1.dist-info/entry_points.txt
mutract-1.1.dist-info/top_level.txt
mutract-1.1.dist-info/RECORD
