Metadata-Version: 2.1
Name: mutract
Version: 1.1
Summary: Extracting single cell variants from bam file
Home-page: https://github.com/singleron-RD/mutract
Author: zhouyiqi
Author-email: zhouyiqi@singleronbio.com
License: UNKNOWN
Platform: UNKNOWN
Classifier: Programming Language :: Python :: 3
Classifier: License :: OSI Approved :: MIT License
Classifier: Operating System :: OS Independent
Requires-Python: >=3.6
Requires-Dist: pysam (>=0.15.0)
Requires-Dist: scipy (>=0.19.1)
Requires-Dist: numpy (>=1.15.4)
Requires-Dist: pandas (==0.23.4)
